whisper_worker/__init__.py
whisper_worker/logging_config.py
whisper_worker/mic.py
whisper_worker/recording_device.py
whisper_worker/settings.py
whisper_worker/transcription.py
whisper_worker/whisper_worker.py
whisper_worker-0.0.27.dist-info/LICENSE
whisper_worker-0.0.27.dist-info/METADATA
whisper_worker-0.0.27.dist-info/WHEEL
whisper_worker-0.0.27.dist-info/RECORD
