Metadata-Version: 2.1
Name: whisper-worker
Version: 0.0.27
Summary: 
License: MIT
Author: C. Thomas Brittain
Author-email: cthomasbrittain@hotmail.com
Requires-Python: >=3.10,<4.0
Classifier: License :: OSI Approved :: MIT License
Classifier: Programming Language :: Python :: 3
Classifier: Programming Language :: Python :: 3.10
Classifier: Programming Language :: Python :: 3.11
Classifier: Programming Language :: Python :: 3.12
Requires-Dist: llvmlite (>=0.44.0,<0.45.0)
Requires-Dist: numba (>=0.61.0,<0.62.0)
Requires-Dist: openai-whisper (>=20240930,<20240931)
Requires-Dist: pip (>=25.0,<26.0)
Requires-Dist: pyaudio (>=0.2.14,<0.3.0)
Requires-Dist: pyyaml (>=6.0.2,<7.0.0)
Requires-Dist: rich (>=13.9.4,<14.0.0)
Requires-Dist: speechrecognition (>=3.14.1,<4.0.0)
